tensortradepy/__init__.py
tensortradepy/exceptions.py
tensortradepy/helpers.py
tensortradepy/solana.py
tensortradepy/tensor.py
tensortradepy-0.2.3.dist-info/METADATA
tensortradepy-0.2.3.dist-info/WHEEL
tensortradepy-0.2.3.dist-info/RECORD
