Metadata-Version: 2.1
Name: tensortradepy
Version: 0.2.3
Summary: Python client for the Tensor Trade API
License: MIT
Author: Defilogist
Author-email: defilogist@thewise.trade
Requires-Python: >=3.8,<4.0
Classifier: License :: OSI Approved :: MIT License
Classifier: Programming Language :: Python :: 3
Classifier: Programming Language :: Python :: 3.8
Classifier: Programming Language :: Python :: 3.9
Classifier: Programming Language :: Python :: 3.10
Classifier: Programming Language :: Python :: 3.11
Classifier: Programming Language :: Python :: 3.12
Requires-Dist: base58 (>=2.1.1,<3.0.0)
Requires-Dist: requests (>=2.31.0,<3.0.0)
Requires-Dist: solana (>=0.30.2,<0.31.0)
